duck_tape_cat/__init__.py
duck_tape_cat/catalog_builder.py
duck_tape_cat/config.py
duck_tape_cat/file_processors.py
duck_tape_cat/file_watcher.py
duck_tape_cat/main.py
duck_tape_cat/utils.py
duck_tape_cat-1.0.0.dist-info/METADATA
duck_tape_cat-1.0.0.dist-info/WHEEL
duck_tape_cat-1.0.0.dist-info/RECORD
