Metadata-Version: 2.3
Name: duck-tape-cat
Version: 1.0.0
Summary: Tapes all your disparate data sources together into a single, queryable DuckDB catalog.
License: MIT
Author: Kenneth Stott
Author-email: ken@kenstott.com
Requires-Python: >=3.8,<4.0
Classifier: License :: OSI Approved :: MIT License
Classifier: Programming Language :: Python :: 3
Classifier: Programming Language :: Python :: 3.8
Classifier: Programming Language :: Python :: 3.9
Classifier: Programming Language :: Python :: 3.10
Classifier: Programming Language :: Python :: 3.11
Classifier: Programming Language :: Python :: 3.12
Classifier: Programming Language :: Python :: 3.13
Provides-Extra: pdf
Requires-Dist: Markdown (>=3.8.2)
Requires-Dist: PyYAML (>=6.0.2)
Requires-Dist: camelot-py[cv] (>=1.0.0) ; extra == "pdf"
Requires-Dist: duckdb (>=1.3.2)
Requires-Dist: fastavro (>=1.11.1)
Requires-Dist: html5lib (>=1.1)
Requires-Dist: lxml (>=6.0.0)
Requires-Dist: openpyxl (>=3.1.5)
Requires-Dist: pandas (>=2.3.1)
Requires-Dist: pyarrow (>=21.0.0)
Requires-Dist: requests (>=2.32.4)
Requires-Dist: s3fs (>=2025.7.0)
Requires-Dist: watchdog (>=6.0.0)
